emw_serializer/__init__.py
emw_serializer/serializer.py
emw_serializer-0.0.2.dist-info/METADATA
emw_serializer-0.0.2.dist-info/WHEEL
emw_serializer-0.0.2.dist-info/entry_points.txt
emw_serializer-0.0.2.dist-info/top_level.txt
emw_serializer-0.0.2.dist-info/RECORD
