Metadata-Version: 2.1
Name: emw-serializer
Version: 0.0.2
Summary: Simple serializer
Home-page: https://github.com/matthew-emw/emw-serializer
Author: Eight Minutes West Limited
Author-email: matthew@eightminuteswest.com
License: MIT
Platform: UNKNOWN
Classifier: License :: OSI Approved :: MIT License
Classifier: Programming Language :: Python :: 3
Classifier: Programming Language :: Python :: 3.7
